ffs/FILE_STRUCTURE.md
ffs/GUIDELINES.md
ffs/__init__.py
ffs/book.py
ffs/classes.py
ffs/cli.py
ffs/problems.py
ffs/spec_version.py
ffs/utils.py
ffs/version.py
flexfs-2.0.2.dist-info/LICENSE
flexfs-2.0.2.dist-info/METADATA
flexfs-2.0.2.dist-info/WHEEL
flexfs-2.0.2.dist-info/entry_points.txt
flexfs-2.0.2.dist-info/top_level.txt
flexfs-2.0.2.dist-info/RECORD
