Metadata-Version: 2.1
Name: flexfs
Version: 2.0.2
Summary: Python tools for querying Flexible File Structure
Home-page: https://github.com/clbarnes/ffs
Author: Chris L. Barnes
License: UNKNOWN
Platform: UNKNOWN
Classifier: Development Status :: 3 - Alpha
Classifier: License :: OSI Approved :: MIT License
Classifier: Programming Language :: Python :: 3
Classifier: Programming Language :: Python :: 3.7
Classifier: Programming Language :: Python :: 3.8
Classifier: Programming Language :: Python :: 3.9
Requires-Python: >=3.7, <4.0
License-File: LICENSE
Requires-Dist: strictyaml
Requires-Dist: toml
Requires-Dist: setuptools
Requires-Dist: click
Requires-Dist: networkx
Requires-Dist: typing-extensions ; python_version < "3.7"
